graphnix/__init__.py
graphnix/control/__init__.py
graphnix/control/colour.py
graphnix/control/cursor.py
graphnix/control/style.py
graphnix/control/text.py
graphnix/input/__init__.py
graphnix/input/console.py
graphnix/input/keyboard_event.py
graphnix/input/mock_input.py
graphnix/input/mouse_event.py
graphnix/interaction/__init__.py
graphnix/interaction/keyboard_interaction.py
graphnix/interaction/layer.py
graphnix/interaction/line.py
graphnix/interaction/mouse_interaction.py
graphnix/interaction/polygon.py
graphnix/interaction/screen.py
graphnix/interaction/singleton.py
graphnix/interaction/temporary_layer.py
Graphnix-0.1.1.dist-info/LICENSE
Graphnix-0.1.1.dist-info/METADATA
Graphnix-0.1.1.dist-info/WHEEL
Graphnix-0.1.1.dist-info/top_level.txt
Graphnix-0.1.1.dist-info/RECORD
