Metadata-Version: 2.1
Name: Graphnix
Version: 0.1.1
Summary: A zero-dependency wrapper for NIX console control in Python
Author-email: Kieran Lock <kieran.lock@outlook.com>
License: MIT License
Project-URL: GitHub, https://github.com/Kieran-Lock/graphnix
Project-URL: Documentation, https://github.com/Kieran-Lock/graphnix/blob/master/DOCUMENTATION.md
Keywords: graphics,nix,ascii,input
Classifier: License :: OSI Approved :: MIT License
Classifier: Programming Language :: Python :: 3.8
Classifier: Intended Audience :: Developers
Requires-Python: >=3.8
License-File: LICENSE
